{
  "exported_at": "2026-04-22T15:25:00.008286+09:00",
  "total": 1,
  "watchlist": [
    {
      "stock_code": "018880",
      "stock_name": "한온시스템",
      "score": 3.0,
      "confidence": 0.5,
      "signal_count": 14,
      "sector": "자동차부품",
      "indicators": {
        "rsi": 51.29,
        "macd": 39.1084,
        "macd_signal": 6.9175,
        "bb_upper": 4236.0,
        "bb_lower": 3645.0,
        "close": 4060,
        "timeframe": "1day",
        "vol_surge": 1.96,
        "_pre_dropna_atr": 220.57143955235443,
        "candle_pattern": "하락장악형",
        "candle_strength": 0.59,
        "weekly_ma5": 3986.0,
        "weekly_ma20": 3763.0,
        "weekly_rsi": 63.3,
        "weekly_trend": "골든",
        "atr_14": 205.83,
        "swing_score": 3.0,
        "swing_mode": true,
        "w52_position_pct": 51.0,
        "w52_high": 5270.0,
        "w52_low": 2800.0,
        "volume_surge": 2.28,
        "day_change_pct": -2.47,
        "foreign_net_buy": 0,
        "institution_net_buy": 0,
        "individual_net_buy": 0,
        "minute_vol_ratio": 0.69,
        "swing_reasons": "MA정배열 | 주봉골든크로스 | 주봉MA20위",
        "market": "KOSPI",
        "sector_momentum": 0.0
      },
      "ranked_score": 42.0
    }
  ]
}