{
  "exported_at": "2026-04-07T15:25:00.007431+09:00",
  "total": 2,
  "watchlist": [
    {
      "stock_code": "006110",
      "stock_name": "삼아알미늄",
      "score": 8.5,
      "confidence": 1.0,
      "signal_count": 19,
      "sector": "비철금속",
      "indicators": {
        "rsi": 60.0,
        "macd": 1497.7158,
        "macd_signal": 1007.7447,
        "bb_upper": 39433.0,
        "bb_lower": 26302.0,
        "close": 38000,
        "timeframe": "1day",
        "vol_surge": 6.14,
        "_pre_dropna_atr": 3803.2098309224584,
        "weekly_ma5": 33560.0,
        "weekly_ma20": 28638.0,
        "weekly_rsi": 68.0,
        "weekly_trend": "골든",
        "atr_14": 4011.12,
        "swing_score": 8.5,
        "swing_mode": true,
        "w52_position_pct": "90.3",
        "w52_high": "40200.0000",
        "w52_low": "17610.0000",
        "volume_surge": 10.5,
        "day_change_pct": -3.95,
        "foreign_net_buy": 0,
        "institution_net_buy": 0,
        "individual_net_buy": 0,
        "minute_vol_ratio": 7.45,
        "swing_reasons": "2일연속상승 | MACD히스토그램↑ | 거래량6.1x | 거래량3x+ | MA정배열 | 주봉골든크로스 | 주봉MA20위 | 상대강도(+5.6%vsKOSPI+2.5%)",
        "market": "KOSPI"
      },
      "ranked_score": 161.5
    },
    {
      "stock_code": "003850",
      "stock_name": "보령",
      "score": 6.0,
      "confidence": 1.0,
      "signal_count": 21,
      "sector": "",
      "indicators": {
        "rsi": 47.68,
        "macd": 0.0,
        "macd_signal": 0.0,
        "bb_upper": 9771.0,
        "bb_lower": 8912.0,
        "close": 9590,
        "timeframe": "1day",
        "vol_surge": 10.01,
        "_pre_dropna_atr": 493.3693972047622,
        "candle_pattern": "역해머",
        "candle_strength": 0.7,
        "weekly_ma5": 9492.0,
        "weekly_ma20": 9336.0,
        "weekly_rsi": 53.8,
        "weekly_trend": "골든",
        "atr_14": 493.37,
        "swing_score": 6.0,
        "swing_mode": true,
        "w52_high": "10370.0000",
        "w52_low": "8750.0000",
        "volume_surge": 4.28,
        "day_change_pct": 6.7,
        "foreign_net_buy": 0,
        "institution_net_buy": 0,
        "individual_net_buy": 0,
        "minute_vol_ratio": 3.8,
        "swing_reasons": "거래량10.0x | 거래량3x+ | 캔들역해머(강) | 주봉골든크로스 | 주봉MA20위 | 상대강도(+5.3%vsKOSPI+1.5%)",
        "market": "KOSPI"
      },
      "ranked_score": 126.0
    }
  ]
}