{
  "exported_at": "2026-04-16T07:00:01.191323+00:00",
  "market_daily": [
    {
      "date": "20260416",
      "kospi_change": 2.21,
      "kosdaq_change": 0.91,
      "foreign_net": 46.44,
      "institution_net": 110.37,
      "individual_net": -180.69,
      "hot_theme_count": 0,
      "momentum_count": 0,
      "crash_count": 0
    },
    {
      "date": "20260415",
      "kospi_change": 2.07,
      "kosdaq_change": 2.72,
      "foreign_net": 55.06,
      "institution_net": -2.24,
      "individual_net": -93.41,
      "hot_theme_count": 40,
      "momentum_count": 60,
      "crash_count": 60
    },
    {
      "date": "20260414",
      "kospi_change": 2.74,
      "kosdaq_change": 2.0,
      "foreign_net": 82.79,
      "institution_net": 125.42,
      "individual_net": -239.15,
      "hot_theme_count": 40,
      "momentum_count": 60,
      "crash_count": 60
    },
    {
      "date": "20260413",
      "kospi_change": -0.86,
      "kosdaq_change": 0.57,
      "foreign_net": -45.64,
      "institution_net": -70.15,
      "individual_net": 74.96,
      "hot_theme_count": 24,
      "momentum_count": 60,
      "crash_count": 60
    },
    {
      "date": "20260410",
      "kospi_change": 1.4,
      "kosdaq_change": 1.64,
      "foreign_net": 110.25,
      "institution_net": -29.38,
      "individual_net": -122.8,
      "hot_theme_count": 40,
      "momentum_count": 60,
      "crash_count": 22
    },
    {
      "date": "20260409",
      "kospi_change": -1.61,
      "kosdaq_change": -1.27,
      "foreign_net": -87.46,
      "institution_net": 20.98,
      "individual_net": 29.5,
      "hot_theme_count": 5,
      "momentum_count": 60,
      "crash_count": 60
    },
    {
      "date": "20260408",
      "kospi_change": 6.87,
      "kosdaq_change": 5.12,
      "foreign_net": 243.85,
      "institution_net": 271.13,
      "individual_net": -541.61,
      "hot_theme_count": 40,
      "momentum_count": 60,
      "crash_count": 60
    },
    {
      "date": "20260407",
      "kospi_change": 0.82,
      "kosdaq_change": -1.02,
      "foreign_net": 40.7,
      "institution_net": -41.41,
      "individual_net": -34.28,
      "hot_theme_count": 3,
      "momentum_count": 52,
      "crash_count": 60
    },
    {
      "date": "20260406",
      "kospi_change": 1.36,
      "kosdaq_change": -1.54,
      "foreign_net": -15.94,
      "institution_net": 83.69,
      "individual_net": -105.02,
      "hot_theme_count": 7,
      "momentum_count": 60,
      "crash_count": 60
    },
    {
      "date": "20260403",
      "kospi_change": 2.74,
      "kosdaq_change": 0.7,
      "foreign_net": 80.86,
      "institution_net": 72.39,
      "individual_net": -209.51,
      "hot_theme_count": 40,
      "momentum_count": 60,
      "crash_count": 60
    }
  ],
  "headlines": [
    "코스피·코스닥 동반 상승",
    "군인공제회, 엠플러스자산운용 에이펙자산운용에 매각 [시그널]",
    "코스피, 중동전쟁 이후 첫 6200선 회복…2.21% 강세 마감",
    "'종전 기대감' 코스피, 6200선 안착",
    "테슬라 AI칩에 '삼성 각인'…파운드리 반격 시작?",
    "'종전 기대감' 코스피, 6200선 안착",
    "개미 차익실현에도…코스피 6200선 상승 마감 [시황]",
    "\"2주 만에 1000p 폭등\"…코스피 6000, '과속 장세' 논쟁",
    "엔알비, 81억 규모 한국세무금융고 생활관 모듈러 제작·설치 계약",
    "'종전 재협상' 기대에 코스피 6200선 회복"
  ]
}