{
  "exported_at": "2026-05-26T07:00:01.682301+00:00",
  "date": "20260526",
  "top_gainers": [
    {
      "stock_name": "삼화콘덴서",
      "stock_code": "001820",
      "change_rate": 30.0,
      "volume": 1936586
    },
    {
      "stock_name": "SK네트웍스",
      "stock_code": "001740",
      "change_rate": 30.0,
      "volume": 64395771
    },
    {
      "stock_name": "티에이치엔",
      "stock_code": "019180",
      "change_rate": 29.93,
      "volume": 4290171
    },
    {
      "stock_name": "삼화전자",
      "stock_code": "011230",
      "change_rate": 29.85,
      "volume": 1320867
    },
    {
      "stock_name": "삼영",
      "stock_code": "003720",
      "change_rate": 23.83,
      "volume": 8221701
    },
    {
      "stock_name": "LG이노텍",
      "stock_code": "011070",
      "change_rate": 23.61,
      "volume": 682399
    },
    {
      "stock_name": "해성디에스",
      "stock_code": "195870",
      "change_rate": 22.63,
      "volume": 744732
    },
    {
      "stock_name": "DB하이텍",
      "stock_code": "000990",
      "change_rate": 21.76,
      "volume": 1040645
    },
    {
      "stock_name": "삼영전자",
      "stock_code": "005680",
      "change_rate": 19.8,
      "volume": 1625925
    },
    {
      "stock_name": "삼성전기",
      "stock_code": "009150",
      "change_rate": 17.31,
      "volume": 1728808
    },
    {
      "stock_name": "삼화콘덴서",
      "stock_code": "001820",
      "change_rate": 30.0,
      "volume": 1936586
    },
    {
      "stock_name": "SK네트웍스",
      "stock_code": "001740",
      "change_rate": 30.0,
      "volume": 64395771
    },
    {
      "stock_name": "티에이치엔",
      "stock_code": "019180",
      "change_rate": 29.93,
      "volume": 4290171
    },
    {
      "stock_name": "삼화전자",
      "stock_code": "011230",
      "change_rate": 29.85,
      "volume": 1320867
    },
    {
      "stock_name": "삼영",
      "stock_code": "003720",
      "change_rate": 23.83,
      "volume": 8221701
    }
  ],
  "top_losers": [
    {
      "stock_name": "신한 블룸버그 레버리지 WTI원유선물 ETN B",
      "stock_code": "500093",
      "change_rate": -13.55,
      "volume": 8156
    },
    {
      "stock_name": "삼성 레버리지 WTI원유 선물 ETN",
      "stock_code": "530031",
      "change_rate": -13.5,
      "volume": 2417257
    },
    {
      "stock_name": "콘텐트리중앙",
      "stock_code": "036420",
      "change_rate": -13.32,
      "volume": 358396
    },
    {
      "stock_name": "삼성 블룸버그 레버리지 WTI원유선물 ETN B",
      "stock_code": "530133",
      "change_rate": -13.2,
      "volume": 24835
    },
    {
      "stock_name": "한투 레버리지WTI원유선물 ETN B",
      "stock_code": "570116",
      "change_rate": -13.1,
      "volume": 1025
    },
    {
      "stock_name": "메리츠 레버리지 WTI원유 선물 ETN(H)",
      "stock_code": "610088",
      "change_rate": -12.9,
      "volume": 569
    },
    {
      "stock_name": "KB S&P 레버리지 WTI원유 선물 ETN B",
      "stock_code": "580068",
      "change_rate": -12.82,
      "volume": 32724
    },
    {
      "stock_name": "SH에너지화학",
      "stock_code": "002360",
      "change_rate": -11.34,
      "volume": 358946
    },
    {
      "stock_name": "하나 S&P 레버리지 WTI원유 선물 ETN B",
      "stock_code": "700029",
      "change_rate": -10.92,
      "volume": 92
    },
    {
      "stock_name": "키움 인버스 2X 반도체TOP10 ETN",
      "stock_code": "760028",
      "change_rate": -9.46,
      "volume": 203589
    },
    {
      "stock_name": "신한 블룸버그 레버리지 WTI원유선물 ETN B",
      "stock_code": "500093",
      "change_rate": -13.55,
      "volume": 8156
    },
    {
      "stock_name": "삼성 레버리지 WTI원유 선물 ETN",
      "stock_code": "530031",
      "change_rate": -13.5,
      "volume": 2417257
    },
    {
      "stock_name": "콘텐트리중앙",
      "stock_code": "036420",
      "change_rate": -13.32,
      "volume": 358396
    },
    {
      "stock_name": "삼성 블룸버그 레버리지 WTI원유선물 ETN B",
      "stock_code": "530133",
      "change_rate": -13.2,
      "volume": 24835
    },
    {
      "stock_name": "한투 레버리지WTI원유선물 ETN B",
      "stock_code": "570116",
      "change_rate": -13.1,
      "volume": 1025
    }
  ]
}