{
  "exported_at": "2026-05-13T07:00:02.108306+00:00",
  "date": "20260513",
  "top_gainers": [
    {
      "stock_name": "한화갤러리아",
      "stock_code": "452260",
      "change_rate": 30.0,
      "volume": 49374110
    },
    {
      "stock_name": "에이프로젠",
      "stock_code": "007460",
      "change_rate": 30.0,
      "volume": 6451694
    },
    {
      "stock_name": "미래산업",
      "stock_code": "025560",
      "change_rate": 29.98,
      "volume": 336861
    },
    {
      "stock_name": "성문전자",
      "stock_code": "014910",
      "change_rate": 29.98,
      "volume": 8221608
    },
    {
      "stock_name": "에이프로젠바이오로직스",
      "stock_code": "003060",
      "change_rate": 29.97,
      "volume": 567576
    },
    {
      "stock_name": "쏘카",
      "stock_code": "403550",
      "change_rate": 29.95,
      "volume": 776363
    },
    {
      "stock_name": "한화갤러리아우",
      "stock_code": "45226K",
      "change_rate": 29.94,
      "volume": 126616
    },
    {
      "stock_name": "성문전자우",
      "stock_code": "014915",
      "change_rate": 29.91,
      "volume": 191665
    },
    {
      "stock_name": "동양고속",
      "stock_code": "084670",
      "change_rate": 29.88,
      "volume": 110667
    },
    {
      "stock_name": "천일고속",
      "stock_code": "000650",
      "change_rate": 29.79,
      "volume": 10997
    },
    {
      "stock_name": "한화갤러리아",
      "stock_code": "452260",
      "change_rate": 30.0,
      "volume": 49374110
    },
    {
      "stock_name": "에이프로젠",
      "stock_code": "007460",
      "change_rate": 30.0,
      "volume": 6451694
    },
    {
      "stock_name": "미래산업",
      "stock_code": "025560",
      "change_rate": 29.98,
      "volume": 336861
    },
    {
      "stock_name": "성문전자",
      "stock_code": "014910",
      "change_rate": 29.98,
      "volume": 8221608
    },
    {
      "stock_name": "에이프로젠바이오로직스",
      "stock_code": "003060",
      "change_rate": 29.97,
      "volume": 567576
    }
  ],
  "top_losers": [
    {
      "stock_name": "대원전선우",
      "stock_code": "006345",
      "change_rate": -21.32,
      "volume": 3498509
    },
    {
      "stock_name": "코스맥스",
      "stock_code": "192820",
      "change_rate": -14.76,
      "volume": 308536
    },
    {
      "stock_name": "하나 인버스 2X 반도체 ETN",
      "stock_code": "700036",
      "change_rate": -11.63,
      "volume": 828202
    },
    {
      "stock_name": "키움 인버스 2X 반도체TOP10 ETN",
      "stock_code": "760028",
      "change_rate": -11.32,
      "volume": 433313
    },
    {
      "stock_name": "카카오페이",
      "stock_code": "377300",
      "change_rate": -11.28,
      "volume": 1017134
    },
    {
      "stock_name": "미래에셋 인버스 2X 반도체 ETN",
      "stock_code": "520099",
      "change_rate": -11.16,
      "volume": 1754958
    },
    {
      "stock_name": "노루페인트우",
      "stock_code": "090355",
      "change_rate": -11.08,
      "volume": 2342
    },
    {
      "stock_name": "코오롱",
      "stock_code": "002020",
      "change_rate": -10.91,
      "volume": 171632
    },
    {
      "stock_name": "대구백화점",
      "stock_code": "006370",
      "change_rate": -10.84,
      "volume": 142540
    },
    {
      "stock_name": "광전자",
      "stock_code": "017900",
      "change_rate": -10.79,
      "volume": 3003739
    },
    {
      "stock_name": "대원전선우",
      "stock_code": "006345",
      "change_rate": -21.32,
      "volume": 3498509
    },
    {
      "stock_name": "코스맥스",
      "stock_code": "192820",
      "change_rate": -14.76,
      "volume": 308536
    },
    {
      "stock_name": "하나 인버스 2X 반도체 ETN",
      "stock_code": "700036",
      "change_rate": -11.63,
      "volume": 828202
    },
    {
      "stock_name": "키움 인버스 2X 반도체TOP10 ETN",
      "stock_code": "760028",
      "change_rate": -11.32,
      "volume": 433313
    },
    {
      "stock_name": "카카오페이",
      "stock_code": "377300",
      "change_rate": -11.28,
      "volume": 1017134
    }
  ]
}