{
  "exported_at": "2026-04-24T07:00:01.522727+00:00",
  "total_stocks": 50,
  "watchlist_all": [
    {
      "stock_code": "000990",
      "stock_name": "DB하이텍",
      "market": "KOSPI",
      "sector": "",
      "signal_count": 92,
      "buy_count": 0,
      "sell_count": 92,
      "avg_confidence": 0.7849956521739131,
      "strategies": [
        "RSI+MACD(swing)"
      ],
      "latest_reason": "RSI과매수(75)",
      "latest_price": 0,
      "latest_at": "2026-04-20T06:00:41.480651"
    },
    {
      "stock_code": "005490",
      "stock_name": "POSCO홀딩스",
      "market": "KOSPI",
      "sector": "철강",
      "signal_count": 77,
      "buy_count": 17,
      "sell_count": 60,
      "avg_confidence": 0.7330116883116892,
      "strategies": [
        "RSI+MACD(swing)"
      ],
      "latest_reason": "RSI과매수(75)",
      "latest_price": 0,
      "latest_at": "2026-04-22T00:00:09.477298"
    },
    {
      "stock_code": "000500",
      "stock_name": "가온전선",
      "market": "KOSPI",
      "sector": "",
      "signal_count": 66,
      "buy_count": 0,
      "sell_count": 66,
      "avg_confidence": 0.8029848484848482,
      "strategies": [
        "RSI+MACD(swing)"
      ],
      "latest_reason": "RSI과매수(75)",
      "latest_price": 0,
      "latest_at": "2026-04-20T06:00:41.480658"
    },
    {
      "stock_code": "090460",
      "stock_name": "비에이치",
      "market": "KOSPI",
      "sector": "",
      "signal_count": 51,
      "buy_count": 0,
      "sell_count": 51,
      "avg_confidence": 0.7929999999999997,
      "strategies": [
        "RSI+MACD(swing)"
      ],
      "latest_reason": "RSI과매수(77)",
      "latest_price": 0,
      "latest_at": "2026-04-20T06:00:41.480655"
    },
    {
      "stock_code": "006400",
      "stock_name": "삼성SDI",
      "market": "KOSPI",
      "sector": "전기전자",
      "signal_count": 51,
      "buy_count": 0,
      "sell_count": 51,
      "avg_confidence": 0.8221666666666667,
      "strategies": [
        "RSI+MACD(swing)"
      ],
      "latest_reason": "RSI과매수(77)",
      "latest_price": 0,
      "latest_at": "2026-04-20T06:00:41.480647"
    },
    {
      "stock_code": "009150",
      "stock_name": "삼성전기",
      "market": "KOSPI",
      "sector": "전자장비와기기",
      "signal_count": 51,
      "buy_count": 0,
      "sell_count": 51,
      "avg_confidence": 0.8612333333333329,
      "strategies": [
        "RSI+MACD(swing)"
      ],
      "latest_reason": "RSI과매수(84)",
      "latest_price": 0,
      "latest_at": "2026-04-21T06:00:28.045500"
    },
    {
      "stock_code": "011500",
      "stock_name": "한농화성",
      "market": "KOSPI",
      "sector": "",
      "signal_count": 50,
      "buy_count": 50,
      "sell_count": 0,
      "avg_confidence": 0.83,
      "strategies": [
        "RSI+MACD(swing)"
      ],
      "latest_reason": "2일연속상승 | MACD히스토그램↑ | RSI모멘텀(62) | 거래량2.1x | MA정배열 | 주봉골든크로스 | 주봉MA20위",
      "latest_price": 0,
      "latest_at": "2026-04-20T06:00:41.480601"
    },
    {
      "stock_code": "010820",
      "stock_name": "퍼스텍",
      "market": "KOSPI",
      "sector": "우주항공과국방",
      "signal_count": 50,
      "buy_count": 0,
      "sell_count": 50,
      "avg_confidence": 0.7726139999999997,
      "strategies": [
        "RSI+MACD(swing)"
      ],
      "latest_reason": "RSI과매수(77)",
      "latest_price": 0,
      "latest_at": "2026-04-20T06:00:41.480644"
    },
    {
      "stock_code": "082740",
      "stock_name": "한화엔진",
      "market": "KOSPI",
      "sector": "",
      "signal_count": 37,
      "buy_count": 17,
      "sell_count": 20,
      "avg_confidence": 0.710516216216217,
      "strategies": [
        "RSI+MACD(swing)"
      ],
      "latest_reason": "MACD히스토그램↑ | 거래량5.7x | 거래량3x+ | MA정배열 | 주봉데드크로스 | 주봉MA20위",
      "latest_price": 0,
      "latest_at": "2026-04-20T06:00:41.480621"
    },
    {
      "stock_code": "018880",
      "stock_name": "한온시스템",
      "market": "KOSPI",
      "sector": "자동차부품",
      "signal_count": 35,
      "buy_count": 35,
      "sell_count": 0,
      "avg_confidence": 0.5762057142857142,
      "strategies": [
        "RSI+MACD(swing)"
      ],
      "latest_reason": "MA정배열 | 주봉골든크로스 | 주봉MA20위",
      "latest_price": 0,
      "latest_at": "2026-04-20T06:00:41.480637"
    },
    {
      "stock_code": "077970",
      "stock_name": "STX엔진",
      "market": "KOSPI",
      "sector": "",
      "signal_count": 34,
      "buy_count": 17,
      "sell_count": 17,
      "avg_confidence": 0.9077999999999998,
      "strategies": [
        "RSI+MACD(swing)"
      ],
      "latest_reason": "2일연속상승 | MACD히스토그램↑ | RSI모멘텀(73) | 거래량15.0x | 거래량3x+ | MA정배열 | 캔들슈팅스타(약세) | 주봉골든크로스 | 주봉MA20위 | 상대강도(+2.8%vsKOSPI+0.6%)",
      "latest_price": 0,
      "latest_at": "2026-04-20T06:00:41.480583"
    },
    {
      "stock_code": "005870",
      "stock_name": "휴니드",
      "market": "KOSPI",
      "sector": "",
      "signal_count": 34,
      "buy_count": 34,
      "sell_count": 0,
      "avg_confidence": 0.58335,
      "strategies": [
        "RSI+MACD(swing)"
      ],
      "latest_reason": "MA정배열 | 주봉골든크로스 | 주봉MA20위",
      "latest_price": 0,
      "latest_at": "2026-04-21T06:00:28.045494"
    },
    {
      "stock_code": "005070",
      "stock_name": "코스모신소재",
      "market": "KOSPI",
      "sector": "",
      "signal_count": 34,
      "buy_count": 17,
      "sell_count": 17,
      "avg_confidence": 0.8759,
      "strategies": [
        "RSI+MACD(swing)"
      ],
      "latest_reason": "2일연속상승 | MACD히스토그램↑ | RSI모멘텀(65) | MA정배열 | 주봉골든크로스 | 주봉MA20위 | 상대강도(+1.9%vsKOSPI+0.6%)",
      "latest_price": 0,
      "latest_at": "2026-04-20T06:00:41.480596"
    },
    {
      "stock_code": "011690",
      "stock_name": "와이투솔루션",
      "market": "KOSPI",
      "sector": "",
      "signal_count": 34,
      "buy_count": 34,
      "sell_count": 0,
      "avg_confidence": 0.6666999999999997,
      "strategies": [
        "RSI+MACD(swing)"
      ],
      "latest_reason": "거래량2.0x | MA정배열 | 주봉골든크로스 | 주봉MA20위",
      "latest_price": 0,
      "latest_at": "2026-04-21T06:00:28.045492"
    },
    {
      "stock_code": "008730",
      "stock_name": "율촌화학",
      "market": "KOSPI",
      "sector": "",
      "signal_count": 34,
      "buy_count": 34,
      "sell_count": 0,
      "avg_confidence": 0.7083000000000004,
      "strategies": [
        "RSI+MACD(swing)"
      ],
      "latest_reason": "MACD히스토그램↑ | RSI모멘텀(72) | 캔들상승장악형(강) | 주봉데드크로스 | 주봉MA20위 | 상대강도(+8.9%vsKOSPI+0.6%)",
      "latest_price": 0,
      "latest_at": "2026-04-20T06:00:41.480625"
    },
    {
      "stock_code": "075580",
      "stock_name": "세진중공업",
      "market": "KOSPI",
      "sector": "",
      "signal_count": 34,
      "buy_count": 34,
      "sell_count": 0,
      "avg_confidence": 0.9166999999999995,
      "strategies": [
        "RSI+MACD(swing)"
      ],
      "latest_reason": "2일연속상승 | MACD히스토그램↑ | RSI모멘텀(60) | 거래량2.9x | MA정배열 | 주봉데드크로스 | 주봉MA20위",
      "latest_price": 0,
      "latest_at": "2026-04-20T06:00:41.480617"
    },
    {
      "stock_code": "020150",
      "stock_name": "롯데에너지머티리얼즈",
      "market": "KOSPI",
      "sector": "",
      "signal_count": 33,
      "buy_count": 0,
      "sell_count": 33,
      "avg_confidence": 0.7793575757575761,
      "strategies": [
        "RSI+MACD(swing)"
      ],
      "latest_reason": "RSI과매수(76)",
      "latest_price": 0,
      "latest_at": "2026-04-22T06:00:12.642889"
    },
    {
      "stock_code": "011070",
      "stock_name": "LG이노텍",
      "market": "KOSPI",
      "sector": "전자장비와기기",
      "signal_count": 33,
      "buy_count": 0,
      "sell_count": 33,
      "avg_confidence": 0.8056060606060608,
      "strategies": [
        "RSI+MACD(swing)"
      ],
      "latest_reason": "RSI과매수(78)",
      "latest_price": 0,
      "latest_at": "2026-04-22T06:00:12.642885"
    },
    {
      "stock_code": "006110",
      "stock_name": "삼아알미늄",
      "market": "KOSPI",
      "sector": "비철금속",
      "signal_count": 33,
      "buy_count": 0,
      "sell_count": 33,
      "avg_confidence": 0.7879757575757574,
      "strategies": [
        "RSI+MACD(swing)"
      ],
      "latest_reason": "RSI과매수(80)",
      "latest_price": 0,
      "latest_at": "2026-04-22T06:00:12.642887"
    },
    {
      "stock_code": "047040",
      "stock_name": "대우건설",
      "market": "KOSPI",
      "sector": "건설",
      "signal_count": 25,
      "buy_count": 0,
      "sell_count": 25,
      "avg_confidence": 0.787516,
      "strategies": [
        "RSI+MACD(swing)"
      ],
      "latest_reason": "RSI과매수(77)",
      "latest_price": 0,
      "latest_at": "2026-04-20T06:00:41.480640"
    },
    {
      "stock_code": "017860",
      "stock_name": "DS단석",
      "market": "KOSPI",
      "sector": "",
      "signal_count": 20,
      "buy_count": 17,
      "sell_count": 3,
      "avg_confidence": 0.9663550000000001,
      "strategies": [
        "RSI+MACD(swing)"
      ],
      "latest_reason": "MACD골든크로스 | RSI모멘텀(52) | 캔들역해머(강) | 주봉골든크로스 | 주봉MA20위 | 상대강도(+2.3%vsKOSPI+0.6%)",
      "latest_price": 0,
      "latest_at": "2026-04-20T06:00:41.480605"
    },
    {
      "stock_code": "001530",
      "stock_name": "DI동일",
      "market": "KOSPI",
      "sector": "섬유,의류,신발,호화품",
      "signal_count": 19,
      "buy_count": 0,
      "sell_count": 19,
      "avg_confidence": 0.7715684210526319,
      "strategies": [
        "RSI+MACD(swing)"
      ],
      "latest_reason": "RSI과매수(77)",
      "latest_price": 0,
      "latest_at": "2026-04-22T06:00:12.642895"
    },
    {
      "stock_code": "004000",
      "stock_name": "롯데정밀화학",
      "market": "KOSPI",
      "sector": "",
      "signal_count": 17,
      "buy_count": 0,
      "sell_count": 17,
      "avg_confidence": 0.7934,
      "strategies": [
        "RSI+MACD(swing)"
      ],
      "latest_reason": "RSI과매수(79)",
      "latest_price": 0,
      "latest_at": "2026-04-24T06:00:59.818625"
    },
    {
      "stock_code": "006260",
      "stock_name": "LS",
      "market": "KOSPI",
      "sector": "",
      "signal_count": 17,
      "buy_count": 0,
      "sell_count": 17,
      "avg_confidence": 0.7571999999999998,
      "strategies": [
        "RSI+MACD(swing)"
      ],
      "latest_reason": "RSI과매수(76)",
      "latest_price": 0,
      "latest_at": "2026-04-24T06:00:59.818603"
    },
    {
      "stock_code": "071970",
      "stock_name": "HD현대마린엔진",
      "market": "KOSPI",
      "sector": "",
      "signal_count": 17,
      "buy_count": 0,
      "sell_count": 17,
      "avg_confidence": 0.7904,
      "strategies": [
        "RSI+MACD(swing)"
      ],
      "latest_reason": "RSI과매수(79)",
      "latest_price": 0,
      "latest_at": "2026-04-24T06:00:59.818585"
    },
    {
      "stock_code": "010060",
      "stock_name": "OCI홀딩스",
      "market": "KOSPI",
      "sector": "",
      "signal_count": 17,
      "buy_count": 0,
      "sell_count": 17,
      "avg_confidence": 0.7723999999999999,
      "strategies": [
        "RSI+MACD(swing)"
      ],
      "latest_reason": "RSI과매수(77)",
      "latest_price": 0,
      "latest_at": "2026-04-24T06:00:59.818560"
    },
    {
      "stock_code": "034220",
      "stock_name": "LG디스플레이",
      "market": "KOSPI",
      "sector": "디스플레이패널",
      "signal_count": 17,
      "buy_count": 17,
      "sell_count": 0,
      "avg_confidence": 0.6667,
      "strategies": [
        "RSI+MACD(swing)"
      ],
      "latest_reason": "거래량2.3x | MA정배열 | 주봉골든크로스 | 주봉MA20위",
      "latest_price": 0,
      "latest_at": "2026-04-24T06:00:59.818514"
    },
    {
      "stock_code": "008060",
      "stock_name": "대덕",
      "market": "KOSPI",
      "sector": "",
      "signal_count": 17,
      "buy_count": 0,
      "sell_count": 17,
      "avg_confidence": 0.7545000000000001,
      "strategies": [
        "RSI+MACD(swing)"
      ],
      "latest_reason": "RSI과매수(75)",
      "latest_price": 0,
      "latest_at": "2026-04-23T06:01:00.660008"
    },
    {
      "stock_code": "002710",
      "stock_name": "TCC스틸",
      "market": "KOSPI",
      "sector": "",
      "signal_count": 17,
      "buy_count": 0,
      "sell_count": 17,
      "avg_confidence": 0.7521000000000002,
      "strategies": [
        "RSI+MACD(swing)"
      ],
      "latest_reason": "RSI과매수(75)",
      "latest_price": 0,
      "latest_at": "2026-04-23T06:01:00.660002"
    },
    {
      "stock_code": "005420",
      "stock_name": "코스모화학",
      "market": "KOSPI",
      "sector": "",
      "signal_count": 17,
      "buy_count": 0,
      "sell_count": 17,
      "avg_confidence": 0.7523999999999998,
      "strategies": [
        "RSI+MACD(swing)"
      ],
      "latest_reason": "RSI과매수(75)",
      "latest_price": 0,
      "latest_at": "2026-04-23T06:01:00.659995"
    }
  ],
  "by_niche": {
    "시장분석": [
      {
        "stock_code": "005490",
        "stock_name": "POSCO홀딩스",
        "market": "KOSPI",
        "sector": "철강",
        "signal_count": 77,
        "buy_count": 17,
        "sell_count": 60,
        "avg_confidence": 0.7330116883116892,
        "strategies": [
          "RSI+MACD(swing)"
        ],
        "latest_reason": "RSI과매수(75)",
        "latest_price": 0,
        "latest_at": "2026-04-22T00:00:09.477298"
      },
      {
        "stock_code": "006400",
        "stock_name": "삼성SDI",
        "market": "KOSPI",
        "sector": "전기전자",
        "signal_count": 51,
        "buy_count": 0,
        "sell_count": 51,
        "avg_confidence": 0.8221666666666667,
        "strategies": [
          "RSI+MACD(swing)"
        ],
        "latest_reason": "RSI과매수(77)",
        "latest_price": 0,
        "latest_at": "2026-04-20T06:00:41.480647"
      },
      {
        "stock_code": "009150",
        "stock_name": "삼성전기",
        "market": "KOSPI",
        "sector": "전자장비와기기",
        "signal_count": 51,
        "buy_count": 0,
        "sell_count": 51,
        "avg_confidence": 0.8612333333333329,
        "strategies": [
          "RSI+MACD(swing)"
        ],
        "latest_reason": "RSI과매수(84)",
        "latest_price": 0,
        "latest_at": "2026-04-21T06:00:28.045500"
      },
      {
        "stock_code": "018260",
        "stock_name": "삼성에스디에스",
        "market": "KOSPI",
        "sector": "",
        "signal_count": 17,
        "buy_count": 17,
        "sell_count": 0,
        "avg_confidence": 0.5833000000000002,
        "strategies": [
          "RSI+MACD(swing)"
        ],
        "latest_reason": "MACD히스토그램↑ | RSI모멘텀(64) | 거래량2.2x | MA정배열 | 주봉데드크로스 | 주봉MA20위",
        "latest_price": 0,
        "latest_at": "2026-04-20T06:00:41.480629"
      },
      {
        "stock_code": "034020",
        "stock_name": "두산에너빌리티",
        "market": "KOSPI",
        "sector": "기계",
        "signal_count": 17,
        "buy_count": 17,
        "sell_count": 0,
        "avg_confidence": 1.0,
        "strategies": [
          "RSI+MACD(swing)"
        ],
        "latest_reason": "MACD히스토그램↑ | RSI모멘텀(63) | MA정배열 | 주봉골든크로스 | 주봉MA20위 | 상대강도(+4.0%vsKOSPI+0.6%)",
        "latest_price": 0,
        "latest_at": "2026-04-20T06:00:41.480614"
      },
      {
        "stock_code": "003670",
        "stock_name": "포스코퓨처엠",
        "market": "KOSPI",
        "sector": "화학",
        "signal_count": 15,
        "buy_count": 15,
        "sell_count": 0,
        "avg_confidence": 1.0,
        "strategies": [
          "RSI+MACD(swing)"
        ],
        "latest_reason": "2일연속상승 | MACD히스토그램↑ | RSI모멘텀(75) | 거래량2.0x | MA정배열 | 주봉골든크로스 | 주봉MA20위",
        "latest_price": 0,
        "latest_at": "2026-04-23T06:01:00.659901"
      },
      {
        "stock_code": "066570",
        "stock_name": "LG전자",
        "market": "KOSPI",
        "sector": "전자제품",
        "signal_count": 2,
        "buy_count": 2,
        "sell_count": 0,
        "avg_confidence": 1.0,
        "strategies": [
          "RSI+MACD(swing)"
        ],
        "latest_reason": "2일연속상승 | MACD히스토그램↑ | RSI모멘텀(66) | MA정배열 | 주봉골든크로스 | 주봉MA20위 | 상대강도(+4.9%vsKOSPI+0.8%)",
        "latest_price": 0,
        "latest_at": "2026-04-23T06:18:01.576420"
      },
      {
        "stock_code": "005930",
        "stock_name": "삼성전자",
        "market": "KOSPI",
        "sector": "반도체",
        "signal_count": 1,
        "buy_count": 1,
        "sell_count": 0,
        "avg_confidence": 0.6,
        "strategies": [
          "swing"
        ],
        "latest_reason": "MACD히스토그램↑ | RSI모멘텀(65) | MA정배열 | 주봉골든크로스 | 주봉MA20위 | 상대강도(+3.2%vsKOSPI-0.3%)",
        "latest_price": 224500.0,
        "latest_at": "2026-04-24T00:18:59.913558",
        "swing_score": 6.0
      }
    ],
    "업종분석": [
      {
        "stock_code": "000990",
        "stock_name": "DB하이텍",
        "market": "KOSPI",
        "sector": "",
        "signal_count": 92,
        "buy_count": 0,
        "sell_count": 92,
        "avg_confidence": 0.7849956521739131,
        "strategies": [
          "RSI+MACD(swing)"
        ],
        "latest_reason": "RSI과매수(75)",
        "latest_price": 0,
        "latest_at": "2026-04-20T06:00:41.480651"
      },
      {
        "stock_code": "000500",
        "stock_name": "가온전선",
        "market": "KOSPI",
        "sector": "",
        "signal_count": 66,
        "buy_count": 0,
        "sell_count": 66,
        "avg_confidence": 0.8029848484848482,
        "strategies": [
          "RSI+MACD(swing)"
        ],
        "latest_reason": "RSI과매수(75)",
        "latest_price": 0,
        "latest_at": "2026-04-20T06:00:41.480658"
      },
      {
        "stock_code": "090460",
        "stock_name": "비에이치",
        "market": "KOSPI",
        "sector": "",
        "signal_count": 51,
        "buy_count": 0,
        "sell_count": 51,
        "avg_confidence": 0.7929999999999997,
        "strategies": [
          "RSI+MACD(swing)"
        ],
        "latest_reason": "RSI과매수(77)",
        "latest_price": 0,
        "latest_at": "2026-04-20T06:00:41.480655"
      },
      {
        "stock_code": "011500",
        "stock_name": "한농화성",
        "market": "KOSPI",
        "sector": "",
        "signal_count": 50,
        "buy_count": 50,
        "sell_count": 0,
        "avg_confidence": 0.83,
        "strategies": [
          "RSI+MACD(swing)"
        ],
        "latest_reason": "2일연속상승 | MACD히스토그램↑ | RSI모멘텀(62) | 거래량2.1x | MA정배열 | 주봉골든크로스 | 주봉MA20위",
        "latest_price": 0,
        "latest_at": "2026-04-20T06:00:41.480601"
      },
      {
        "stock_code": "010820",
        "stock_name": "퍼스텍",
        "market": "KOSPI",
        "sector": "우주항공과국방",
        "signal_count": 50,
        "buy_count": 0,
        "sell_count": 50,
        "avg_confidence": 0.7726139999999997,
        "strategies": [
          "RSI+MACD(swing)"
        ],
        "latest_reason": "RSI과매수(77)",
        "latest_price": 0,
        "latest_at": "2026-04-20T06:00:41.480644"
      },
      {
        "stock_code": "082740",
        "stock_name": "한화엔진",
        "market": "KOSPI",
        "sector": "",
        "signal_count": 37,
        "buy_count": 17,
        "sell_count": 20,
        "avg_confidence": 0.710516216216217,
        "strategies": [
          "RSI+MACD(swing)"
        ],
        "latest_reason": "MACD히스토그램↑ | 거래량5.7x | 거래량3x+ | MA정배열 | 주봉데드크로스 | 주봉MA20위",
        "latest_price": 0,
        "latest_at": "2026-04-20T06:00:41.480621"
      },
      {
        "stock_code": "018880",
        "stock_name": "한온시스템",
        "market": "KOSPI",
        "sector": "자동차부품",
        "signal_count": 35,
        "buy_count": 35,
        "sell_count": 0,
        "avg_confidence": 0.5762057142857142,
        "strategies": [
          "RSI+MACD(swing)"
        ],
        "latest_reason": "MA정배열 | 주봉골든크로스 | 주봉MA20위",
        "latest_price": 0,
        "latest_at": "2026-04-20T06:00:41.480637"
      },
      {
        "stock_code": "077970",
        "stock_name": "STX엔진",
        "market": "KOSPI",
        "sector": "",
        "signal_count": 34,
        "buy_count": 17,
        "sell_count": 17,
        "avg_confidence": 0.9077999999999998,
        "strategies": [
          "RSI+MACD(swing)"
        ],
        "latest_reason": "2일연속상승 | MACD히스토그램↑ | RSI모멘텀(73) | 거래량15.0x | 거래량3x+ | MA정배열 | 캔들슈팅스타(약세) | 주봉골든크로스 | 주봉MA20위 | 상대강도(+2.8%vsKOSPI+0.6%)",
        "latest_price": 0,
        "latest_at": "2026-04-20T06:00:41.480583"
      },
      {
        "stock_code": "005870",
        "stock_name": "휴니드",
        "market": "KOSPI",
        "sector": "",
        "signal_count": 34,
        "buy_count": 34,
        "sell_count": 0,
        "avg_confidence": 0.58335,
        "strategies": [
          "RSI+MACD(swing)"
        ],
        "latest_reason": "MA정배열 | 주봉골든크로스 | 주봉MA20위",
        "latest_price": 0,
        "latest_at": "2026-04-21T06:00:28.045494"
      },
      {
        "stock_code": "005070",
        "stock_name": "코스모신소재",
        "market": "KOSPI",
        "sector": "",
        "signal_count": 34,
        "buy_count": 17,
        "sell_count": 17,
        "avg_confidence": 0.8759,
        "strategies": [
          "RSI+MACD(swing)"
        ],
        "latest_reason": "2일연속상승 | MACD히스토그램↑ | RSI모멘텀(65) | MA정배열 | 주봉골든크로스 | 주봉MA20위 | 상대강도(+1.9%vsKOSPI+0.6%)",
        "latest_price": 0,
        "latest_at": "2026-04-20T06:00:41.480596"
      }
    ],
    "테마분석": [
      {
        "stock_code": "000990",
        "stock_name": "DB하이텍",
        "market": "KOSPI",
        "sector": "",
        "signal_count": 92,
        "buy_count": 0,
        "sell_count": 92,
        "avg_confidence": 0.7849956521739131,
        "strategies": [
          "RSI+MACD(swing)"
        ],
        "latest_reason": "RSI과매수(75)",
        "latest_price": 0,
        "latest_at": "2026-04-20T06:00:41.480651"
      },
      {
        "stock_code": "005490",
        "stock_name": "POSCO홀딩스",
        "market": "KOSPI",
        "sector": "철강",
        "signal_count": 77,
        "buy_count": 17,
        "sell_count": 60,
        "avg_confidence": 0.7330116883116892,
        "strategies": [
          "RSI+MACD(swing)"
        ],
        "latest_reason": "RSI과매수(75)",
        "latest_price": 0,
        "latest_at": "2026-04-22T00:00:09.477298"
      },
      {
        "stock_code": "000500",
        "stock_name": "가온전선",
        "market": "KOSPI",
        "sector": "",
        "signal_count": 66,
        "buy_count": 0,
        "sell_count": 66,
        "avg_confidence": 0.8029848484848482,
        "strategies": [
          "RSI+MACD(swing)"
        ],
        "latest_reason": "RSI과매수(75)",
        "latest_price": 0,
        "latest_at": "2026-04-20T06:00:41.480658"
      },
      {
        "stock_code": "090460",
        "stock_name": "비에이치",
        "market": "KOSPI",
        "sector": "",
        "signal_count": 51,
        "buy_count": 0,
        "sell_count": 51,
        "avg_confidence": 0.7929999999999997,
        "strategies": [
          "RSI+MACD(swing)"
        ],
        "latest_reason": "RSI과매수(77)",
        "latest_price": 0,
        "latest_at": "2026-04-20T06:00:41.480655"
      },
      {
        "stock_code": "006400",
        "stock_name": "삼성SDI",
        "market": "KOSPI",
        "sector": "전기전자",
        "signal_count": 51,
        "buy_count": 0,
        "sell_count": 51,
        "avg_confidence": 0.8221666666666667,
        "strategies": [
          "RSI+MACD(swing)"
        ],
        "latest_reason": "RSI과매수(77)",
        "latest_price": 0,
        "latest_at": "2026-04-20T06:00:41.480647"
      },
      {
        "stock_code": "009150",
        "stock_name": "삼성전기",
        "market": "KOSPI",
        "sector": "전자장비와기기",
        "signal_count": 51,
        "buy_count": 0,
        "sell_count": 51,
        "avg_confidence": 0.8612333333333329,
        "strategies": [
          "RSI+MACD(swing)"
        ],
        "latest_reason": "RSI과매수(84)",
        "latest_price": 0,
        "latest_at": "2026-04-21T06:00:28.045500"
      },
      {
        "stock_code": "011500",
        "stock_name": "한농화성",
        "market": "KOSPI",
        "sector": "",
        "signal_count": 50,
        "buy_count": 50,
        "sell_count": 0,
        "avg_confidence": 0.83,
        "strategies": [
          "RSI+MACD(swing)"
        ],
        "latest_reason": "2일연속상승 | MACD히스토그램↑ | RSI모멘텀(62) | 거래량2.1x | MA정배열 | 주봉골든크로스 | 주봉MA20위",
        "latest_price": 0,
        "latest_at": "2026-04-20T06:00:41.480601"
      },
      {
        "stock_code": "010820",
        "stock_name": "퍼스텍",
        "market": "KOSPI",
        "sector": "우주항공과국방",
        "signal_count": 50,
        "buy_count": 0,
        "sell_count": 50,
        "avg_confidence": 0.7726139999999997,
        "strategies": [
          "RSI+MACD(swing)"
        ],
        "latest_reason": "RSI과매수(77)",
        "latest_price": 0,
        "latest_at": "2026-04-20T06:00:41.480644"
      },
      {
        "stock_code": "082740",
        "stock_name": "한화엔진",
        "market": "KOSPI",
        "sector": "",
        "signal_count": 37,
        "buy_count": 17,
        "sell_count": 20,
        "avg_confidence": 0.710516216216217,
        "strategies": [
          "RSI+MACD(swing)"
        ],
        "latest_reason": "MACD히스토그램↑ | 거래량5.7x | 거래량3x+ | MA정배열 | 주봉데드크로스 | 주봉MA20위",
        "latest_price": 0,
        "latest_at": "2026-04-20T06:00:41.480621"
      },
      {
        "stock_code": "018880",
        "stock_name": "한온시스템",
        "market": "KOSPI",
        "sector": "자동차부품",
        "signal_count": 35,
        "buy_count": 35,
        "sell_count": 0,
        "avg_confidence": 0.5762057142857142,
        "strategies": [
          "RSI+MACD(swing)"
        ],
        "latest_reason": "MA정배열 | 주봉골든크로스 | 주봉MA20위",
        "latest_price": 0,
        "latest_at": "2026-04-20T06:00:41.480637"
      }
    ],
    "수급분석": [
      {
        "stock_code": "000990",
        "stock_name": "DB하이텍",
        "market": "KOSPI",
        "sector": "",
        "signal_count": 92,
        "buy_count": 0,
        "sell_count": 92,
        "avg_confidence": 0.7849956521739131,
        "strategies": [
          "RSI+MACD(swing)"
        ],
        "latest_reason": "RSI과매수(75)",
        "latest_price": 0,
        "latest_at": "2026-04-20T06:00:41.480651"
      },
      {
        "stock_code": "005490",
        "stock_name": "POSCO홀딩스",
        "market": "KOSPI",
        "sector": "철강",
        "signal_count": 77,
        "buy_count": 17,
        "sell_count": 60,
        "avg_confidence": 0.7330116883116892,
        "strategies": [
          "RSI+MACD(swing)"
        ],
        "latest_reason": "RSI과매수(75)",
        "latest_price": 0,
        "latest_at": "2026-04-22T00:00:09.477298"
      },
      {
        "stock_code": "000500",
        "stock_name": "가온전선",
        "market": "KOSPI",
        "sector": "",
        "signal_count": 66,
        "buy_count": 0,
        "sell_count": 66,
        "avg_confidence": 0.8029848484848482,
        "strategies": [
          "RSI+MACD(swing)"
        ],
        "latest_reason": "RSI과매수(75)",
        "latest_price": 0,
        "latest_at": "2026-04-20T06:00:41.480658"
      },
      {
        "stock_code": "090460",
        "stock_name": "비에이치",
        "market": "KOSPI",
        "sector": "",
        "signal_count": 51,
        "buy_count": 0,
        "sell_count": 51,
        "avg_confidence": 0.7929999999999997,
        "strategies": [
          "RSI+MACD(swing)"
        ],
        "latest_reason": "RSI과매수(77)",
        "latest_price": 0,
        "latest_at": "2026-04-20T06:00:41.480655"
      },
      {
        "stock_code": "006400",
        "stock_name": "삼성SDI",
        "market": "KOSPI",
        "sector": "전기전자",
        "signal_count": 51,
        "buy_count": 0,
        "sell_count": 51,
        "avg_confidence": 0.8221666666666667,
        "strategies": [
          "RSI+MACD(swing)"
        ],
        "latest_reason": "RSI과매수(77)",
        "latest_price": 0,
        "latest_at": "2026-04-20T06:00:41.480647"
      },
      {
        "stock_code": "009150",
        "stock_name": "삼성전기",
        "market": "KOSPI",
        "sector": "전자장비와기기",
        "signal_count": 51,
        "buy_count": 0,
        "sell_count": 51,
        "avg_confidence": 0.8612333333333329,
        "strategies": [
          "RSI+MACD(swing)"
        ],
        "latest_reason": "RSI과매수(84)",
        "latest_price": 0,
        "latest_at": "2026-04-21T06:00:28.045500"
      },
      {
        "stock_code": "011500",
        "stock_name": "한농화성",
        "market": "KOSPI",
        "sector": "",
        "signal_count": 50,
        "buy_count": 50,
        "sell_count": 0,
        "avg_confidence": 0.83,
        "strategies": [
          "RSI+MACD(swing)"
        ],
        "latest_reason": "2일연속상승 | MACD히스토그램↑ | RSI모멘텀(62) | 거래량2.1x | MA정배열 | 주봉골든크로스 | 주봉MA20위",
        "latest_price": 0,
        "latest_at": "2026-04-20T06:00:41.480601"
      },
      {
        "stock_code": "010820",
        "stock_name": "퍼스텍",
        "market": "KOSPI",
        "sector": "우주항공과국방",
        "signal_count": 50,
        "buy_count": 0,
        "sell_count": 50,
        "avg_confidence": 0.7726139999999997,
        "strategies": [
          "RSI+MACD(swing)"
        ],
        "latest_reason": "RSI과매수(77)",
        "latest_price": 0,
        "latest_at": "2026-04-20T06:00:41.480644"
      },
      {
        "stock_code": "082740",
        "stock_name": "한화엔진",
        "market": "KOSPI",
        "sector": "",
        "signal_count": 37,
        "buy_count": 17,
        "sell_count": 20,
        "avg_confidence": 0.710516216216217,
        "strategies": [
          "RSI+MACD(swing)"
        ],
        "latest_reason": "MACD히스토그램↑ | 거래량5.7x | 거래량3x+ | MA정배열 | 주봉데드크로스 | 주봉MA20위",
        "latest_price": 0,
        "latest_at": "2026-04-20T06:00:41.480621"
      },
      {
        "stock_code": "018880",
        "stock_name": "한온시스템",
        "market": "KOSPI",
        "sector": "자동차부품",
        "signal_count": 35,
        "buy_count": 35,
        "sell_count": 0,
        "avg_confidence": 0.5762057142857142,
        "strategies": [
          "RSI+MACD(swing)"
        ],
        "latest_reason": "MA정배열 | 주봉골든크로스 | 주봉MA20위",
        "latest_price": 0,
        "latest_at": "2026-04-20T06:00:41.480637"
      }
    ]
  }
}